timestreams/__init__.py
timestreams-0.0.1a1.dist-info/WHEEL
timestreams-0.0.1a1.dist-info/METADATA
timestreams-0.0.1a1.dist-info/RECORD
