Metadata-Version: 2.1
Name: timestreams
Version: 0.0.1a1
Summary: A placeholder for a future kaskada project
License: Apache-2.0
Author: Kaskada
Author-email: maintainers@kaskada.io
Requires-Python: >=3.8.2,<4.0.0
Classifier: License :: OSI Approved :: Apache Software License
Classifier: Programming Language :: Python :: 3
Classifier: Programming Language :: Python :: 3.9
Classifier: Programming Language :: Python :: 3.10
Classifier: Programming Language :: Python :: 3.11
